try_except_ai/__init__.py
try_except_ai/try_except_ai.py
try_except_ai-0.1.1.dist-info/WHEEL
try_except_ai-0.1.1.dist-info/METADATA
try_except_ai-0.1.1.dist-info/RECORD
