Metadata-Version: 2.1
Name: try-except-ai
Version: 0.1.1
Summary: A Python package to handle exceptions and suggest resolutions using OpenAI
Home-page: https://github.com/etnalab/try-except-ai
License: MIT
Keywords: openai,exceptions,ai
Author: Federico Ulfo
Author-email: federicoulfo@gmail.com
Requires-Python: >=3.9,<4.0
Classifier: Development Status :: 3 - Alpha
Classifier: Intended Audience :: Developers
Classifier: License :: OSI Approved :: MIT License
Classifier: Programming Language :: Python :: 3
Classifier: Programming Language :: Python :: 3.10
Classifier: Programming Language :: Python :: 3.6
Classifier: Programming Language :: Python :: 3.7
Classifier: Programming Language :: Python :: 3.8
Classifier: Programming Language :: Python :: 3.9
Requires-Dist: openai (>=0.27.4,<0.28.0)
Project-URL: Repository, https://github.com/etnalab/try-except-ai
